serializable/__init__.py
serializable/helpers.py
serializable/primitive_types.py
serializable/serializable.py
serializable-0.4.1.dist-info/LICENSE
serializable-0.4.1.dist-info/METADATA
serializable-0.4.1.dist-info/WHEEL
serializable-0.4.1.dist-info/top_level.txt
serializable-0.4.1.dist-info/RECORD
