Metadata-Version: 2.1
Name: serializable
Version: 0.4.1
Summary: Base class with serialization helpers for user-defined Python objects
Home-page: https://github.com/iskandr/serializable
Author: Alex Rubinsteyn
Author-email: alex@openvax.org
License: http://www.apache.org/licenses/LICENSE-2.0.html
Classifier: Development Status :: 3 - Alpha
Classifier: Environment :: Console
Classifier: Operating System :: OS Independent
Classifier: License :: OSI Approved :: Apache Software License
Classifier: Programming Language :: Python
License-File: LICENSE
Requires-Dist: typechecks >=0.0.2
Requires-Dist: simplejson
